{
  "id": 275,
  "name": "Unending Sundew",
  "cost": 0,
  "type": "summon",
  "attack": 1,
  "defense": 1,
  "tribe": "treefolk",
  "rarity": "common",
  "description": "When Unending Sundew is tributed, exile it instead of sacrificing it. \n Exile Unending Sundew from your graveyard: return it to play at the beginning of your next Draw phase.",
  "triggeredEffects": [  
    {
      "trigger": "tribute",
      "scope": "selfOnly",
      "effects": [  
        { 
          "effect": "sendToZone",
          "destination": "exile"
        }
      ]
    }
  ],
  "activatedEffects": [
    {
      "conditions": [
        {
          "condition": "inZone",
          "zone": "graveyard"
        }
      ],
      "costType": "exile",
      "effects": [  
        {
          "effect": "sendToZone",
          "destination": "play",
          "phase": "draw",
          "phaseOfPlayer": "player"
        }
      ]
    }
  ] 
}